enfobench/__init__.py
enfobench/__version__.py
enfobench/py.typed
enfobench/core/__init__.py
enfobench/core/dataset.py
enfobench/core/model.py
enfobench/datasets/__init__.py
enfobench/datasets/base.py
enfobench/datasets/electricity_demand.py
enfobench/datasets/gas_demand.py
enfobench/datasets/pv_generation.py
enfobench/datasets/utils.py
enfobench/evaluation/__init__.py
enfobench/evaluation/client.py
enfobench/evaluation/evaluate.py
enfobench/evaluation/filters.py
enfobench/evaluation/metrics.py
enfobench/evaluation/server.py
enfobench/evaluation/utils.py
enfobench/visualization/__init__.py
enfobench/visualization/demand.py
enfobench-0.8.0.dist-info/METADATA
enfobench-0.8.0.dist-info/WHEEL
enfobench-0.8.0.dist-info/licenses/LICENCE
enfobench-0.8.0.dist-info/RECORD
