Metadata-Version: 2.4
Name: enfobench
Version: 0.8.0
Summary: Energy forecast benchmarking toolkit.
Project-URL: Documentation, https://github.com/attila-balint-kul/energy-forecast-benchmark-toolkit#readme
Project-URL: Issues, https://github.com/attila-balint-kul/energy-forecast-benchmark-toolkit/issues
Project-URL: Source, https://github.com/attila-balint-kul/energy-forecast-benchmark-toolkit
Author-email: attila.balint@kuleuven.be
License-Expression: BSD-3-Clause
License-File: LICENCE
Keywords: benchmarking,energy,forecasting
Classifier: Development Status :: 4 - Beta
Classifier: Intended Audience :: Science/Research
Classifier: License :: OSI Approved :: BSD License
Classifier: Natural Language :: English
Classifier: Operating System :: OS Independent
Classifier: Programming Language :: Python :: 3 :: Only
Classifier: Programming Language :: Python :: 3.10
Classifier: Programming Language :: Python :: 3.11
Classifier: Programming Language :: Python :: 3.12
Classifier: Programming Language :: Python :: Implementation :: CPython
Classifier: Programming Language :: Python :: Implementation :: PyPy
Classifier: Topic :: Scientific/Engineering
Requires-Python: >=3.10
Requires-Dist: duckdb<2.0.0,>=1.0.0
Requires-Dist: fastapi<1.0.0,>=0.68.0
Requires-Dist: pandas>=1.5
Requires-Dist: pyarrow>=13.0.0
Requires-Dist: pydantic>=2.0.0
Requires-Dist: python-multipart>=0.0.0
Requires-Dist: requests>=2.26.0
Requires-Dist: tqdm>=4.60.0
Requires-Dist: uvicorn>=0.20.0
Provides-Extra: visualization
Requires-Dist: matplotlib; extra == 'visualization'
Requires-Dist: seaborn; extra == 'visualization'
Requires-Dist: statsmodels; extra == 'visualization'
